steamreviews/__init__.py
steamreviews/download_reviews.py
steamreviews/tests/__init__.py
steamreviews/tests/test_steamreviews.py
steamreviews-0.9.5.dist-info/LICENSE
steamreviews-0.9.5.dist-info/METADATA
steamreviews-0.9.5.dist-info/WHEEL
steamreviews-0.9.5.dist-info/top_level.txt
steamreviews-0.9.5.dist-info/RECORD
