Metadata-Version: 2.1
Name: steamreviews
Version: 0.9.5
Summary: An API to download Steam reviews
Home-page: https://github.com/woctezuma/download-steam-reviews
Author: Wok
Author-email: wok@tuta.io
License: UNKNOWN
Download-URL: https://github.com/woctezuma/download-steam-reviews/archive/0.9.5.tar.gz
Keywords: steam,review,reviews,download,api
Platform: UNKNOWN
Classifier: Development Status :: 5 - Production/Stable
Classifier: Topic :: Games/Entertainment
Classifier: Programming Language :: Python :: 3
Classifier: License :: OSI Approved :: MIT License
Classifier: Operating System :: OS Independent
Requires-Python: >=3
Requires-Dist: requests
